loveletter/__init__.py
loveletter/bot.py
loveletter/cards.py
loveletter/game.py
loveletter/users.py
loveletter/tests/__init__.py
loveletter/tests/test_bot.py
loveletter-0.0.5.dist-info/LICENSE
loveletter-0.0.5.dist-info/METADATA
loveletter-0.0.5.dist-info/WHEEL
loveletter-0.0.5.dist-info/entry_points.txt
loveletter-0.0.5.dist-info/top_level.txt
loveletter-0.0.5.dist-info/RECORD
