Metadata-Version: 2.1
Name: loveletter
Version: 0.0.5
Summary: UNKNOWN
Home-page: https://github.com/kst179/LoveLetter
Author: Konstantin Kozlovtsev
License: UNKNOWN
Platform: UNKNOWN
Classifier: Programming Language :: Python :: 3
Classifier: License :: OSI Approved :: MIT License
Classifier: Operating System :: OS Independent
